{
  "cookpad": [
    {
      "timestamp": "2025-10-09T21:24:25Z",
      "status": "updated",
      "hash": "f4c2c32b8dbd065c38e8da73ed42d5d2",
      "change_detected": true
    },
    {
      "timestamp": "2025-10-09T21:36:37Z",
      "status": "updated",
      "hash": "211a3c4685910b72e85a6d09d262c8e1",
      "change_detected": true
    },
    {
      "timestamp": "2025-10-09T21:47:39Z",
      "status": "unchanged",
      "hash": "211a3c4685910b72e85a6d09d262c8e1",
      "change_detected": false
    },
    {
      "timestamp": "2025-10-09T21:58:03Z",
      "status": "updated",
      "hash": "51a84c88626c98907b52ad96d5e36f59",
      "change_detected": true
    },
    {
      "timestamp": "2025-10-09T22:24:13Z",
      "status": "updated",
      "hash": "2e5c11eb7176c82f50a33bd84ddb67d4",
      "change_detected": true
    },
    {
      "timestamp": "2025-10-09T22:38:45Z",
      "status": "updated",
      "hash": "d77c4b861e9719a206c0e5f354c79e7c",
      "change_detected": true
    },
    {
      "timestamp": "2025-10-09T22:49:15Z",
      "status": "unchanged",
      "hash": "d77c4b861e9719a206c0e5f354c79e7c",
      "change_detected": false
    },
    {
      "timestamp": "2025-10-09T22:59:45Z",
      "status": "updated",
      "hash": "d76dd70755be0df66b7563168c5a782b",
      "change_detected": true
    },
    {
      "timestamp": "2025-10-09T23:23:32Z",
      "status": "updated",
      "hash": "5ee8abeab57c31c80d1fc8591e53d66b",
      "change_detected": true
    },
    {
      "timestamp": "2025-10-09T23:35:59Z",
      "status": "updated",
      "hash": "8a40fc7ba457424c2be93ded35e6a1c3",
      "change_detected": true
    },
    {
      "timestamp": "2025-10-09T23:47:03Z",
      "status": "unchanged",
      "hash": "8a40fc7ba457424c2be93ded35e6a1c3",
      "change_detected": false
    },
    {
      "timestamp": "2025-10-09T23:57:38Z",
      "status": "updated",
      "hash": "56ac94ff22d2ff6e192f3b4cfe470eb8",
      "change_detected": true
    },
    {
      "timestamp": "2025-10-10T01:53:20Z",
      "status": "updated",
      "hash": "79a891076565d863fb4b7e0e2e48072e",
      "change_detected": true
    },
    {
      "timestamp": "2025-10-10T02:57:47Z",
      "status": "updated",
      "hash": "4ef11003cf5d060a6b67886c02455169",
      "change_detected": true
    },
    {
      "timestamp": "2025-10-10T03:35:30Z",
      "status": "updated",
      "hash": "b60205bba86980b0e8a5a1d8dc8cf3e1",
      "change_detected": true
    },
    {
      "timestamp": "2025-10-10T03:52:09Z",
      "status": "unchanged",
      "hash": "b60205bba86980b0e8a5a1d8dc8cf3e1",
      "change_detected": false
    },
    {
      "timestamp": "2025-10-10T04:15:09Z",
      "status": "updated",
      "hash": "57d323e6acd7d10998e64225babe082d",
      "change_detected": true
    },
    {
      "timestamp": "2025-10-10T04:37:41Z",
      "status": "updated",
      "hash": "9688ccdfa3a454682413317fa10b3d31",
      "change_detected": true
    },
    {
      "timestamp": "2025-10-10T04:49:53Z",
      "status": "unchanged",
      "hash": "9688ccdfa3a454682413317fa10b3d31",
      "change_detected": false
    },
    {
      "timestamp": "2025-10-10T05:00:32Z",
      "status": "updated",
      "hash": "c009716972ab4d7325a8bbe7e9c6d140",
      "change_detected": true
    },
    {
      "timestamp": "2025-10-10T05:27:40Z",
      "status": "updated",
      "hash": "bf33d3ab71dc0ae62d06d3a1ba35754a",
      "change_detected": true
    },
    {
      "timestamp": "2025-10-10T05:43:07Z",
      "status": "updated",
      "hash": "d1041a5b55549b60835e01c8656bc50a",
      "change_detected": true
    },
    {
      "timestamp": "2025-10-10T05:53:39Z",
      "status": "updated",
      "hash": "cd1731ed1d6878aba1d7b5b4ce830b62",
      "change_detected": true
    },
    {
      "timestamp": "2025-10-10T06:24:05Z",
      "status": "updated",
      "hash": "331db2887823a96f0bb54ed7f78c3e44",
      "change_detected": true
    },
    {
      "timestamp": "2025-10-10T06:49:17Z",
      "status": "updated",
      "hash": "7c31aecbae51fbe90f8631142df58e50",
      "change_detected": true
    },
    {
      "timestamp": "2025-10-10T07:00:13Z",
      "status": "updated",
      "hash": "0cd352079bf4a636fd3113cea3951ad5",
      "change_detected": true
    },
    {
      "timestamp": "2025-10-10T07:25:37Z",
      "status": "updated",
      "hash": "c874f4f9d274a6ea1ed3a0d7e6fa54ed",
      "change_detected": true
    },
    {
      "timestamp": "2025-10-10T07:38:30Z",
      "status": "updated",
      "hash": "75d1fbd4ecbb1349036b9e5d1583682f",
      "change_detected": true
    },
    {
      "timestamp": "2025-10-10T07:49:24Z",
      "status": "unchanged",
      "hash": "75d1fbd4ecbb1349036b9e5d1583682f",
      "change_detected": false
    },
    {
      "timestamp": "2025-10-10T08:00:14Z",
      "status": "updated",
      "hash": "8fff2ee8861e56a5f74804696d2b497e",
      "change_detected": true
    },
    {
      "timestamp": "2025-10-10T08:34:42Z",
      "status": "updated",
      "hash": "b2dc278fe4f296762a725114abf3ac4f",
      "change_detected": true
    },
    {
      "timestamp": "2025-10-10T08:51:13Z",
      "status": "unchanged",
      "hash": "b2dc278fe4f296762a725114abf3ac4f",
      "change_detected": false
    },
    {
      "timestamp": "2025-10-10T09:12:30Z",
      "status": "updated",
      "hash": "cd26b7d6b011133999656fbb4c4f850c",
      "change_detected": true
    },
    {
      "timestamp": "2025-10-10T09:32:46Z",
      "status": "updated",
      "hash": "6e21d6a02589926c9617b01dbad026c9",
      "change_detected": true
    },
    {
      "timestamp": "2025-10-10T09:44:50Z",
      "status": "unchanged",
      "hash": "6e21d6a02589926c9617b01dbad026c9",
      "change_detected": false
    },
    {
      "timestamp": "2025-10-10T09:55:30Z",
      "status": "updated",
      "hash": "1710c628d154190c2668f1633537728d",
      "change_detected": true
    },
    {
      "timestamp": "2025-10-10T10:21:20Z",
      "status": "updated",
      "hash": "881a3f754ea37700948f345ce75835df",
      "change_detected": true
    },
    {
      "timestamp": "2025-10-10T10:40:02Z",
      "status": "updated",
      "hash": "e7e2d2838454f803f2c8923ab2461205",
      "change_detected": true
    },
    {
      "timestamp": "2025-10-10T10:51:01Z",
      "status": "unchanged",
      "hash": "e7e2d2838454f803f2c8923ab2461205",
      "change_detected": false
    },
    {
      "timestamp": "2025-10-10T11:09:05Z",
      "status": "updated",
      "hash": "6c32870266024f8f9383434ec862b503",
      "change_detected": true
    },
    {
      "timestamp": "2025-10-10T11:26:01Z",
      "status": "updated",
      "hash": "376cbbe41bb1946bce5307788915a2ea",
      "change_detected": true
    },
    {
      "timestamp": "2025-10-10T11:38:05Z",
      "status": "updated",
      "hash": "8d80f7d4287a0c3a865ad502f0de2aea",
      "change_detected": true
    },
    {
      "timestamp": "2025-10-10T11:49:08Z",
      "status": "unchanged",
      "hash": "8d80f7d4287a0c3a865ad502f0de2aea",
      "change_detected": false
    },
    {
      "timestamp": "2025-10-10T11:59:50Z",
      "status": "updated",
      "hash": "317405aa81f50a232f08c37f8bf6e843",
      "change_detected": true
    },
    {
      "timestamp": "2025-10-10T12:54:10Z",
      "status": "updated",
      "hash": "bed3c4d5e9ac4cecc123306e4a982fc0",
      "change_detected": true
    },
    {
      "timestamp": "2025-10-10T13:26:21Z",
      "status": "updated",
      "hash": "136e78e91100085dedcf5a75608e69c4",
      "change_detected": true
    },
    {
      "timestamp": "2025-10-10T13:44:44Z",
      "status": "updated",
      "hash": "dbd708f51c32b5ef5da27099fdeef932",
      "change_detected": true
    },
    {
      "timestamp": "2025-10-10T13:55:29Z",
      "status": "updated",
      "hash": "de3a18b52e9a4fb4936cbb2e9f7a1d13",
      "change_detected": true
    },
    {
      "timestamp": "2025-10-10T14:19:39Z",
      "status": "updated",
      "hash": "6c0ccda68b77b7ff6cf3b73f1d6681d1",
      "change_detected": true
    },
    {
      "timestamp": "2025-10-10T14:39:05Z",
      "status": "updated",
      "hash": "30b6b2b0f49a7ef811f4fe9f98f9ae4c",
      "change_detected": true
    },
    {
      "timestamp": "2025-10-10T14:50:08Z",
      "status": "unchanged",
      "hash": "30b6b2b0f49a7ef811f4fe9f98f9ae4c",
      "change_detected": false
    },
    {
      "timestamp": "2025-10-10T15:01:21Z",
      "status": "updated",
      "hash": "01364bc6d1e50e56ec8fadb5e0b5baa2",
      "change_detected": true
    },
    {
      "timestamp": "2025-10-10T15:27:28Z",
      "status": "unchanged",
      "hash": "01364bc6d1e50e56ec8fadb5e0b5baa2",
      "change_detected": false
    },
    {
      "timestamp": "2025-10-10T15:41:56Z",
      "status": "unchanged",
      "hash": "01364bc6d1e50e56ec8fadb5e0b5baa2",
      "change_detected": false
    },
    {
      "timestamp": "2025-10-10T15:52:43Z",
      "status": "unchanged",
      "hash": "01364bc6d1e50e56ec8fadb5e0b5baa2",
      "change_detected": false
    },
    {
      "timestamp": "2025-10-10T16:16:55Z",
      "status": "updated",
      "hash": "f9a0aea059fafc77fa0a189cb2fc16ef",
      "change_detected": true
    },
    {
      "timestamp": "2025-10-10T16:40:54Z",
      "status": "updated",
      "hash": "65fbfbecf5f14e3636b8bdc9b4523a80",
      "change_detected": true
    },
    {
      "timestamp": "2025-10-10T16:53:10Z",
      "status": "updated",
      "hash": "d83ed18f335946d7539848171324baf2",
      "change_detected": true
    },
    {
      "timestamp": "2025-10-10T17:13:38Z",
      "status": "updated",
      "hash": "4a38f9f8a2e687bcd93defb79fc54739",
      "change_detected": true
    },
    {
      "timestamp": "2025-10-10T17:30:57Z",
      "status": "unchanged",
      "hash": "4a38f9f8a2e687bcd93defb79fc54739",
      "change_detected": false
    },
    {
      "timestamp": "2025-10-10T17:42:38Z",
      "status": "updated",
      "hash": "d34368e1b78efaed66a0973a6011ee0a",
      "change_detected": true
    },
    {
      "timestamp": "2025-10-10T17:53:26Z",
      "status": "updated",
      "hash": "c9115440764522d9033c8377388c9b8c",
      "change_detected": true
    },
    {
      "timestamp": "2025-10-10T18:22:11Z",
      "status": "updated",
      "hash": "9676ce7300718ec8936d7968b52df491",
      "change_detected": true
    },
    {
      "timestamp": "2025-10-10T18:44:54Z",
      "status": "updated",
      "hash": "45b87bbd57adef2ca11c17043daeb764",
      "change_detected": true
    },
    {
      "timestamp": "2025-10-10T18:55:29Z",
      "status": "updated",
      "hash": "4df6cd08d2cb1a1c2e696c5c03696352",
      "change_detected": true
    },
    {
      "timestamp": "2025-10-10T19:15:46Z",
      "status": "updated",
      "hash": "e1f0fac8ade6cdc4b75c941cbd097e9b",
      "change_detected": true
    },
    {
      "timestamp": "2025-10-10T19:27:58Z",
      "status": "unchanged",
      "hash": "e1f0fac8ade6cdc4b75c941cbd097e9b",
      "change_detected": false
    },
    {
      "timestamp": "2025-10-10T19:39:41Z",
      "status": "updated",
      "hash": "3525b81b3e316503b2dd5c83c18f5759",
      "change_detected": true
    },
    {
      "timestamp": "2025-10-10T19:50:19Z",
      "status": "unchanged",
      "hash": "3525b81b3e316503b2dd5c83c18f5759",
      "change_detected": false
    },
    {
      "timestamp": "2025-10-10T20:12:15Z",
      "status": "updated",
      "hash": "1106cc33010a3dfc505a86a724af4214",
      "change_detected": true
    },
    {
      "timestamp": "2025-10-10T20:31:22Z",
      "status": "updated",
      "hash": "9e311ce29a7cf112e94eaaf3ed5aec4f",
      "change_detected": true
    },
    {
      "timestamp": "2025-10-10T20:44:15Z",
      "status": "updated",
      "hash": "cbc0f8076d2e9760d2d0b283a48078c8",
      "change_detected": true
    },
    {
      "timestamp": "2025-10-10T20:54:58Z",
      "status": "updated",
      "hash": "4d6b1727d630c9de313a96b662b8b48f",
      "change_detected": true
    },
    {
      "timestamp": "2025-10-10T21:15:31Z",
      "status": "updated",
      "hash": "f3a4181b51c15027da1544b6d4382d2f",
      "change_detected": true
    },
    {
      "timestamp": "2025-10-10T21:29:11Z",
      "status": "updated",
      "hash": "0286be8e3293bd523606003656223a21",
      "change_detected": true
    },
    {
      "timestamp": "2025-10-10T21:40:03Z",
      "status": "updated",
      "hash": "cf49b79a76c3c477ab7f9b7ae6b8dd40",
      "change_detected": true
    },
    {
      "timestamp": "2025-10-10T21:50:59Z",
      "status": "unchanged",
      "hash": "cf49b79a76c3c477ab7f9b7ae6b8dd40",
      "change_detected": false
    },
    {
      "timestamp": "2025-10-10T22:08:52Z",
      "status": "updated",
      "hash": "8b0e93064dce3b88ba90393fca9ba8d7",
      "change_detected": true
    },
    {
      "timestamp": "2025-10-10T22:29:43Z",
      "status": "updated",
      "hash": "99a8416c67346c36e6fa87eebe2885db",
      "change_detected": true
    },
    {
      "timestamp": "2025-10-10T22:42:11Z",
      "status": "updated",
      "hash": "24bcb77def2fdd2e4b3813902c7cdd00",
      "change_detected": true
    },
    {
      "timestamp": "2025-10-10T22:52:51Z",
      "status": "updated",
      "hash": "81940836749ef8a5b2c05bc8aef3e285",
      "change_detected": true
    },
    {
      "timestamp": "2025-10-10T23:12:08Z",
      "status": "unchanged",
      "hash": "81940836749ef8a5b2c05bc8aef3e285",
      "change_detected": false
    },
    {
      "timestamp": "2025-10-10T23:28:02Z",
      "status": "updated",
      "hash": "bd46e3fb2c9a8b23e56b476beb36a149",
      "change_detected": true
    },
    {
      "timestamp": "2025-10-10T23:39:29Z",
      "status": "updated",
      "hash": "82cae1a3f61f9964e2dcdede98c74785",
      "change_detected": true
    },
    {
      "timestamp": "2025-10-10T23:50:26Z",
      "status": "unchanged",
      "hash": "82cae1a3f61f9964e2dcdede98c74785",
      "change_detected": false
    },
    {
      "timestamp": "2025-10-11T00:38:40Z",
      "status": "updated",
      "hash": "7ec95e77d38ffd86b7877e5277770f17",
      "change_detected": true
    },
    {
      "timestamp": "2025-10-11T02:08:26Z",
      "status": "updated",
      "hash": "2bcfbf4db5c8c648a33a0a3b07741a8d",
      "change_detected": true
    },
    {
      "timestamp": "2025-10-11T03:01:59Z",
      "status": "updated",
      "hash": "41d7f66f24cae332ed2228748a7a5144",
      "change_detected": true
    },
    {
      "timestamp": "2025-10-11T03:33:13Z",
      "status": "updated",
      "hash": "0ff5d636d10937b6adb85e491490eefd",
      "change_detected": true
    },
    {
      "timestamp": "2025-10-11T03:46:33Z",
      "status": "unchanged",
      "hash": "0ff5d636d10937b6adb85e491490eefd",
      "change_detected": false
    },
    {
      "timestamp": "2025-10-11T03:57:04Z",
      "status": "updated",
      "hash": "bffb6deeeb1bfc30d2484c64a6abaee4",
      "change_detected": true
    },
    {
      "timestamp": "2025-10-11T04:26:21Z",
      "status": "updated",
      "hash": "faa8dce7ee1492b223a7ec910c9b0bcb",
      "change_detected": true
    },
    {
      "timestamp": "2025-10-11T04:41:28Z",
      "status": "updated",
      "hash": "735302d3e6090b5688a55cca31f4b027",
      "change_detected": true
    },
    {
      "timestamp": "2025-10-11T04:52:16Z",
      "status": "updated",
      "hash": "7022d736aec540135e86ecb3530570d0",
      "change_detected": true
    },
    {
      "timestamp": "2025-10-11T05:11:40Z",
      "status": "unchanged",
      "hash": "7022d736aec540135e86ecb3530570d0",
      "change_detected": false
    },
    {
      "timestamp": "2025-10-11T05:30:59Z",
      "status": "updated",
      "hash": "f7d70c75146b47697cded3a707d8c3e5",
      "change_detected": true
    },
    {
      "timestamp": "2025-10-11T05:42:46Z",
      "status": "updated",
      "hash": "b313e7a45b17f7445a48e82a19811c14",
      "change_detected": true
    },
    {
      "timestamp": "2025-10-11T05:53:41Z",
      "status": "updated",
      "hash": "a3b2b25e829dd193157df55bc56e96bd",
      "change_detected": true
    },
    {
      "timestamp": "2025-10-11T06:21:05Z",
      "status": "updated",
      "hash": "a0013ca87477fd31d1835c2222f9f7d5",
      "change_detected": true
    },
    {
      "timestamp": "2025-10-11T06:42:32Z",
      "status": "updated",
      "hash": "482bbd727077f294efe3d78636d7b6b9",
      "change_detected": true
    }
  ],
  "test": [
    {
      "timestamp": "2025-10-09T18:30:40Z",
      "status": "unchanged",
      "hash": "3529baac6f9972f4dfd3ad6c012e28db",
      "change_detected": false
    },
    {
      "timestamp": "2025-10-09T18:50:21Z",
      "status": "unchanged",
      "hash": "3529baac6f9972f4dfd3ad6c012e28db",
      "change_detected": false
    },
    {
      "timestamp": "2025-10-09T19:01:23Z",
      "status": "unchanged",
      "hash": "3529baac6f9972f4dfd3ad6c012e28db",
      "change_detected": false
    },
    {
      "timestamp": "2025-10-09T19:22:47Z",
      "status": "unchanged",
      "hash": "3529baac6f9972f4dfd3ad6c012e28db",
      "change_detected": false
    },
    {
      "timestamp": "2025-10-09T19:35:25Z",
      "status": "unchanged",
      "hash": "3529baac6f9972f4dfd3ad6c012e28db",
      "change_detected": false
    },
    {
      "timestamp": "2025-10-09T19:45:37Z",
      "status": "unchanged",
      "hash": "3529baac6f9972f4dfd3ad6c012e28db",
      "change_detected": false
    },
    {
      "timestamp": "2025-10-09T19:56:09Z",
      "status": "unchanged",
      "hash": "3529baac6f9972f4dfd3ad6c012e28db",
      "change_detected": false
    },
    {
      "timestamp": "2025-10-09T20:23:36Z",
      "status": "unchanged",
      "hash": "3529baac6f9972f4dfd3ad6c012e28db",
      "change_detected": false
    },
    {
      "timestamp": "2025-10-09T20:39:33Z",
      "status": "unchanged",
      "hash": "3529baac6f9972f4dfd3ad6c012e28db",
      "change_detected": false
    },
    {
      "timestamp": "2025-10-09T21:24:34Z",
      "status": "unchanged",
      "hash": "3529baac6f9972f4dfd3ad6c012e28db",
      "change_detected": false
    },
    {
      "timestamp": "2025-10-09T21:36:44Z",
      "status": "unchanged",
      "hash": "3529baac6f9972f4dfd3ad6c012e28db",
      "change_detected": false
    },
    {
      "timestamp": "2025-10-09T21:47:47Z",
      "status": "unchanged",
      "hash": "3529baac6f9972f4dfd3ad6c012e28db",
      "change_detected": false
    },
    {
      "timestamp": "2025-10-09T21:58:12Z",
      "status": "unchanged",
      "hash": "3529baac6f9972f4dfd3ad6c012e28db",
      "change_detected": false
    },
    {
      "timestamp": "2025-10-09T22:24:22Z",
      "status": "unchanged",
      "hash": "3529baac6f9972f4dfd3ad6c012e28db",
      "change_detected": false
    },
    {
      "timestamp": "2025-10-09T22:38:53Z",
      "status": "unchanged",
      "hash": "3529baac6f9972f4dfd3ad6c012e28db",
      "change_detected": false
    },
    {
      "timestamp": "2025-10-09T22:49:23Z",
      "status": "unchanged",
      "hash": "3529baac6f9972f4dfd3ad6c012e28db",
      "change_detected": false
    },
    {
      "timestamp": "2025-10-09T22:59:53Z",
      "status": "unchanged",
      "hash": "3529baac6f9972f4dfd3ad6c012e28db",
      "change_detected": false
    },
    {
      "timestamp": "2025-10-09T23:23:41Z",
      "status": "unchanged",
      "hash": "3529baac6f9972f4dfd3ad6c012e28db",
      "change_detected": false
    },
    {
      "timestamp": "2025-10-09T23:36:07Z",
      "status": "unchanged",
      "hash": "3529baac6f9972f4dfd3ad6c012e28db",
      "change_detected": false
    },
    {
      "timestamp": "2025-10-09T23:47:11Z",
      "status": "unchanged",
      "hash": "3529baac6f9972f4dfd3ad6c012e28db",
      "change_detected": false
    },
    {
      "timestamp": "2025-10-09T23:57:46Z",
      "status": "unchanged",
      "hash": "3529baac6f9972f4dfd3ad6c012e28db",
      "change_detected": false
    },
    {
      "timestamp": "2025-10-10T01:53:29Z",
      "status": "unchanged",
      "hash": "3529baac6f9972f4dfd3ad6c012e28db",
      "change_detected": false
    },
    {
      "timestamp": "2025-10-10T02:57:56Z",
      "status": "unchanged",
      "hash": "3529baac6f9972f4dfd3ad6c012e28db",
      "change_detected": false
    },
    {
      "timestamp": "2025-10-10T03:35:39Z",
      "status": "unchanged",
      "hash": "3529baac6f9972f4dfd3ad6c012e28db",
      "change_detected": false
    },
    {
      "timestamp": "2025-10-10T03:52:17Z",
      "status": "unchanged",
      "hash": "3529baac6f9972f4dfd3ad6c012e28db",
      "change_detected": false
    },
    {
      "timestamp": "2025-10-10T04:37:49Z",
      "status": "unchanged",
      "hash": "3529baac6f9972f4dfd3ad6c012e28db",
      "change_detected": false
    },
    {
      "timestamp": "2025-10-10T04:50:02Z",
      "status": "unchanged",
      "hash": "3529baac6f9972f4dfd3ad6c012e28db",
      "change_detected": false
    },
    {
      "timestamp": "2025-10-10T05:00:41Z",
      "status": "unchanged",
      "hash": "3529baac6f9972f4dfd3ad6c012e28db",
      "change_detected": false
    },
    {
      "timestamp": "2025-10-10T05:27:49Z",
      "status": "unchanged",
      "hash": "3529baac6f9972f4dfd3ad6c012e28db",
      "change_detected": false
    },
    {
      "timestamp": "2025-10-10T05:43:16Z",
      "status": "unchanged",
      "hash": "3529baac6f9972f4dfd3ad6c012e28db",
      "change_detected": false
    },
    {
      "timestamp": "2025-10-10T05:53:48Z",
      "status": "unchanged",
      "hash": "3529baac6f9972f4dfd3ad6c012e28db",
      "change_detected": false
    },
    {
      "timestamp": "2025-10-10T06:24:14Z",
      "status": "unchanged",
      "hash": "3529baac6f9972f4dfd3ad6c012e28db",
      "change_detected": false
    },
    {
      "timestamp": "2025-10-10T06:49:25Z",
      "status": "unchanged",
      "hash": "3529baac6f9972f4dfd3ad6c012e28db",
      "change_detected": false
    },
    {
      "timestamp": "2025-10-10T07:38:40Z",
      "status": "unchanged",
      "hash": "3529baac6f9972f4dfd3ad6c012e28db",
      "change_detected": false
    },
    {
      "timestamp": "2025-10-10T07:49:32Z",
      "status": "unchanged",
      "hash": "3529baac6f9972f4dfd3ad6c012e28db",
      "change_detected": false
    },
    {
      "timestamp": "2025-10-10T08:00:23Z",
      "status": "unchanged",
      "hash": "3529baac6f9972f4dfd3ad6c012e28db",
      "change_detected": false
    },
    {
      "timestamp": "2025-10-10T08:34:50Z",
      "status": "unchanged",
      "hash": "3529baac6f9972f4dfd3ad6c012e28db",
      "change_detected": false
    },
    {
      "timestamp": "2025-10-10T08:51:22Z",
      "status": "unchanged",
      "hash": "3529baac6f9972f4dfd3ad6c012e28db",
      "change_detected": false
    },
    {
      "timestamp": "2025-10-10T09:12:38Z",
      "status": "unchanged",
      "hash": "3529baac6f9972f4dfd3ad6c012e28db",
      "change_detected": false
    },
    {
      "timestamp": "2025-10-10T09:32:55Z",
      "status": "unchanged",
      "hash": "3529baac6f9972f4dfd3ad6c012e28db",
      "change_detected": false
    },
    {
      "timestamp": "2025-10-10T09:44:57Z",
      "status": "unchanged",
      "hash": "3529baac6f9972f4dfd3ad6c012e28db",
      "change_detected": false
    },
    {
      "timestamp": "2025-10-10T09:55:39Z",
      "status": "unchanged",
      "hash": "3529baac6f9972f4dfd3ad6c012e28db",
      "change_detected": false
    },
    {
      "timestamp": "2025-10-10T10:21:28Z",
      "status": "unchanged",
      "hash": "3529baac6f9972f4dfd3ad6c012e28db",
      "change_detected": false
    },
    {
      "timestamp": "2025-10-10T10:40:10Z",
      "status": "unchanged",
      "hash": "3529baac6f9972f4dfd3ad6c012e28db",
      "change_detected": false
    },
    {
      "timestamp": "2025-10-10T10:51:09Z",
      "status": "unchanged",
      "hash": "3529baac6f9972f4dfd3ad6c012e28db",
      "change_detected": false
    },
    {
      "timestamp": "2025-10-10T11:09:13Z",
      "status": "unchanged",
      "hash": "3529baac6f9972f4dfd3ad6c012e28db",
      "change_detected": false
    },
    {
      "timestamp": "2025-10-10T11:26:10Z",
      "status": "unchanged",
      "hash": "3529baac6f9972f4dfd3ad6c012e28db",
      "change_detected": false
    },
    {
      "timestamp": "2025-10-10T11:49:17Z",
      "status": "unchanged",
      "hash": "3529baac6f9972f4dfd3ad6c012e28db",
      "change_detected": false
    },
    {
      "timestamp": "2025-10-10T11:59:59Z",
      "status": "unchanged",
      "hash": "3529baac6f9972f4dfd3ad6c012e28db",
      "change_detected": false
    },
    {
      "timestamp": "2025-10-10T12:54:19Z",
      "status": "unchanged",
      "hash": "3529baac6f9972f4dfd3ad6c012e28db",
      "change_detected": false
    },
    {
      "timestamp": "2025-10-10T13:26:30Z",
      "status": "unchanged",
      "hash": "3529baac6f9972f4dfd3ad6c012e28db",
      "change_detected": false
    },
    {
      "timestamp": "2025-10-10T13:44:53Z",
      "status": "unchanged",
      "hash": "3529baac6f9972f4dfd3ad6c012e28db",
      "change_detected": false
    },
    {
      "timestamp": "2025-10-10T13:55:37Z",
      "status": "unchanged",
      "hash": "3529baac6f9972f4dfd3ad6c012e28db",
      "change_detected": false
    },
    {
      "timestamp": "2025-10-10T14:39:14Z",
      "status": "unchanged",
      "hash": "3529baac6f9972f4dfd3ad6c012e28db",
      "change_detected": false
    },
    {
      "timestamp": "2025-10-10T14:50:17Z",
      "status": "unchanged",
      "hash": "3529baac6f9972f4dfd3ad6c012e28db",
      "change_detected": false
    },
    {
      "timestamp": "2025-10-10T15:27:37Z",
      "status": "unchanged",
      "hash": "3529baac6f9972f4dfd3ad6c012e28db",
      "change_detected": false
    },
    {
      "timestamp": "2025-10-10T15:42:04Z",
      "status": "unchanged",
      "hash": "3529baac6f9972f4dfd3ad6c012e28db",
      "change_detected": false
    },
    {
      "timestamp": "2025-10-10T15:52:51Z",
      "status": "unchanged",
      "hash": "3529baac6f9972f4dfd3ad6c012e28db",
      "change_detected": false
    },
    {
      "timestamp": "2025-10-10T16:17:03Z",
      "status": "unchanged",
      "hash": "3529baac6f9972f4dfd3ad6c012e28db",
      "change_detected": false
    },
    {
      "timestamp": "2025-10-10T16:41:04Z",
      "status": "unchanged",
      "hash": "3529baac6f9972f4dfd3ad6c012e28db",
      "change_detected": false
    },
    {
      "timestamp": "2025-10-10T16:53:19Z",
      "status": "unchanged",
      "hash": "3529baac6f9972f4dfd3ad6c012e28db",
      "change_detected": false
    },
    {
      "timestamp": "2025-10-10T17:13:47Z",
      "status": "unchanged",
      "hash": "3529baac6f9972f4dfd3ad6c012e28db",
      "change_detected": false
    },
    {
      "timestamp": "2025-10-10T17:31:05Z",
      "status": "unchanged",
      "hash": "3529baac6f9972f4dfd3ad6c012e28db",
      "change_detected": false
    },
    {
      "timestamp": "2025-10-10T17:42:46Z",
      "status": "unchanged",
      "hash": "3529baac6f9972f4dfd3ad6c012e28db",
      "change_detected": false
    },
    {
      "timestamp": "2025-10-10T17:53:34Z",
      "status": "unchanged",
      "hash": "3529baac6f9972f4dfd3ad6c012e28db",
      "change_detected": false
    },
    {
      "timestamp": "2025-10-10T18:22:19Z",
      "status": "unchanged",
      "hash": "3529baac6f9972f4dfd3ad6c012e28db",
      "change_detected": false
    },
    {
      "timestamp": "2025-10-10T18:45:03Z",
      "status": "unchanged",
      "hash": "3529baac6f9972f4dfd3ad6c012e28db",
      "change_detected": false
    },
    {
      "timestamp": "2025-10-10T18:55:38Z",
      "status": "unchanged",
      "hash": "3529baac6f9972f4dfd3ad6c012e28db",
      "change_detected": false
    },
    {
      "timestamp": "2025-10-10T19:15:55Z",
      "status": "unchanged",
      "hash": "3529baac6f9972f4dfd3ad6c012e28db",
      "change_detected": false
    },
    {
      "timestamp": "2025-10-10T19:28:06Z",
      "status": "unchanged",
      "hash": "3529baac6f9972f4dfd3ad6c012e28db",
      "change_detected": false
    },
    {
      "timestamp": "2025-10-10T19:39:49Z",
      "status": "unchanged",
      "hash": "3529baac6f9972f4dfd3ad6c012e28db",
      "change_detected": false
    },
    {
      "timestamp": "2025-10-10T19:50:27Z",
      "status": "unchanged",
      "hash": "3529baac6f9972f4dfd3ad6c012e28db",
      "change_detected": false
    },
    {
      "timestamp": "2025-10-10T20:12:23Z",
      "status": "unchanged",
      "hash": "3529baac6f9972f4dfd3ad6c012e28db",
      "change_detected": false
    },
    {
      "timestamp": "2025-10-10T20:31:31Z",
      "status": "unchanged",
      "hash": "3529baac6f9972f4dfd3ad6c012e28db",
      "change_detected": false
    },
    {
      "timestamp": "2025-10-10T20:55:07Z",
      "status": "unchanged",
      "hash": "3529baac6f9972f4dfd3ad6c012e28db",
      "change_detected": false
    },
    {
      "timestamp": "2025-10-10T21:15:39Z",
      "status": "unchanged",
      "hash": "3529baac6f9972f4dfd3ad6c012e28db",
      "change_detected": false
    },
    {
      "timestamp": "2025-10-10T21:29:21Z",
      "status": "unchanged",
      "hash": "3529baac6f9972f4dfd3ad6c012e28db",
      "change_detected": false
    },
    {
      "timestamp": "2025-10-10T21:40:12Z",
      "status": "unchanged",
      "hash": "3529baac6f9972f4dfd3ad6c012e28db",
      "change_detected": false
    },
    {
      "timestamp": "2025-10-10T21:51:07Z",
      "status": "unchanged",
      "hash": "3529baac6f9972f4dfd3ad6c012e28db",
      "change_detected": false
    },
    {
      "timestamp": "2025-10-10T22:09:01Z",
      "status": "unchanged",
      "hash": "3529baac6f9972f4dfd3ad6c012e28db",
      "change_detected": false
    },
    {
      "timestamp": "2025-10-10T22:29:52Z",
      "status": "unchanged",
      "hash": "3529baac6f9972f4dfd3ad6c012e28db",
      "change_detected": false
    },
    {
      "timestamp": "2025-10-10T22:42:20Z",
      "status": "unchanged",
      "hash": "3529baac6f9972f4dfd3ad6c012e28db",
      "change_detected": false
    },
    {
      "timestamp": "2025-10-10T22:53:00Z",
      "status": "unchanged",
      "hash": "3529baac6f9972f4dfd3ad6c012e28db",
      "change_detected": false
    },
    {
      "timestamp": "2025-10-10T23:28:11Z",
      "status": "unchanged",
      "hash": "3529baac6f9972f4dfd3ad6c012e28db",
      "change_detected": false
    },
    {
      "timestamp": "2025-10-10T23:39:38Z",
      "status": "unchanged",
      "hash": "3529baac6f9972f4dfd3ad6c012e28db",
      "change_detected": false
    },
    {
      "timestamp": "2025-10-10T23:50:34Z",
      "status": "unchanged",
      "hash": "3529baac6f9972f4dfd3ad6c012e28db",
      "change_detected": false
    },
    {
      "timestamp": "2025-10-11T00:38:49Z",
      "status": "unchanged",
      "hash": "3529baac6f9972f4dfd3ad6c012e28db",
      "change_detected": false
    },
    {
      "timestamp": "2025-10-11T02:08:34Z",
      "status": "unchanged",
      "hash": "3529baac6f9972f4dfd3ad6c012e28db",
      "change_detected": false
    },
    {
      "timestamp": "2025-10-11T03:33:23Z",
      "status": "unchanged",
      "hash": "3529baac6f9972f4dfd3ad6c012e28db",
      "change_detected": false
    },
    {
      "timestamp": "2025-10-11T03:46:42Z",
      "status": "unchanged",
      "hash": "3529baac6f9972f4dfd3ad6c012e28db",
      "change_detected": false
    },
    {
      "timestamp": "2025-10-11T03:57:13Z",
      "status": "unchanged",
      "hash": "3529baac6f9972f4dfd3ad6c012e28db",
      "change_detected": false
    },
    {
      "timestamp": "2025-10-11T04:26:29Z",
      "status": "unchanged",
      "hash": "3529baac6f9972f4dfd3ad6c012e28db",
      "change_detected": false
    },
    {
      "timestamp": "2025-10-11T04:41:36Z",
      "status": "unchanged",
      "hash": "3529baac6f9972f4dfd3ad6c012e28db",
      "change_detected": false
    },
    {
      "timestamp": "2025-10-11T04:52:24Z",
      "status": "unchanged",
      "hash": "3529baac6f9972f4dfd3ad6c012e28db",
      "change_detected": false
    },
    {
      "timestamp": "2025-10-11T05:11:49Z",
      "status": "unchanged",
      "hash": "3529baac6f9972f4dfd3ad6c012e28db",
      "change_detected": false
    },
    {
      "timestamp": "2025-10-11T05:31:08Z",
      "status": "unchanged",
      "hash": "3529baac6f9972f4dfd3ad6c012e28db",
      "change_detected": false
    },
    {
      "timestamp": "2025-10-11T05:42:54Z",
      "status": "unchanged",
      "hash": "3529baac6f9972f4dfd3ad6c012e28db",
      "change_detected": false
    },
    {
      "timestamp": "2025-10-11T05:53:49Z",
      "status": "unchanged",
      "hash": "3529baac6f9972f4dfd3ad6c012e28db",
      "change_detected": false
    },
    {
      "timestamp": "2025-10-11T06:21:13Z",
      "status": "unchanged",
      "hash": "3529baac6f9972f4dfd3ad6c012e28db",
      "change_detected": false
    },
    {
      "timestamp": "2025-10-11T06:42:42Z",
      "status": "unchanged",
      "hash": "3529baac6f9972f4dfd3ad6c012e28db",
      "change_detected": false
    }
  ],
  "test2": [
    {
      "timestamp": "2025-10-09T18:30:47Z",
      "status": "updated",
      "hash": "cdd4d599f8c295d3f6a50dddac8128f8",
      "change_detected": true
    },
    {
      "timestamp": "2025-10-09T18:50:28Z",
      "status": "updated",
      "hash": "42b1929b1ab06d82dd34705ee7bc3e23",
      "change_detected": true
    },
    {
      "timestamp": "2025-10-09T19:01:30Z",
      "status": "updated",
      "hash": "84065c68d6732af7506b0185cafb3748",
      "change_detected": true
    },
    {
      "timestamp": "2025-10-09T19:22:53Z",
      "status": "updated",
      "hash": "50dfda1b27308ba21a514838256bcc15",
      "change_detected": true
    },
    {
      "timestamp": "2025-10-09T19:35:35Z",
      "status": "updated",
      "hash": "7673721d3b9456b9c0efc0f4fe29eb07",
      "change_detected": true
    },
    {
      "timestamp": "2025-10-09T19:45:44Z",
      "status": "updated",
      "hash": "5812a4c225223b3e8a40c1505748bd8b",
      "change_detected": true
    },
    {
      "timestamp": "2025-10-09T19:56:15Z",
      "status": "updated",
      "hash": "3b519de1dcd953a9602aab6a9e1a5d73",
      "change_detected": true
    },
    {
      "timestamp": "2025-10-09T20:23:43Z",
      "status": "updated",
      "hash": "0e280784dbeab462a948aaa589044398",
      "change_detected": true
    },
    {
      "timestamp": "2025-10-09T20:39:41Z",
      "status": "updated",
      "hash": "f9f5ef3e8c4842c0166a454d8e3396f7",
      "change_detected": true
    },
    {
      "timestamp": "2025-10-09T21:24:42Z",
      "status": "unchanged",
      "hash": "c92e44b8a7fcc64f3e7537427b0a3cf5",
      "change_detected": false
    },
    {
      "timestamp": "2025-10-09T21:36:51Z",
      "status": "updated",
      "hash": "f30b9dc5a81624d5afc58b87a0adab06",
      "change_detected": true
    },
    {
      "timestamp": "2025-10-09T21:47:53Z",
      "status": "updated",
      "hash": "5880fc5c150cde20f8cc7b26c33f54ec",
      "change_detected": true
    },
    {
      "timestamp": "2025-10-09T21:58:20Z",
      "status": "updated",
      "hash": "57a946589217821a9f69f46876715397",
      "change_detected": true
    },
    {
      "timestamp": "2025-10-09T22:24:29Z",
      "status": "updated",
      "hash": "359b01e70384b834f501e5c667ea2807",
      "change_detected": true
    },
    {
      "timestamp": "2025-10-09T22:39:00Z",
      "status": "updated",
      "hash": "5241b03812fc57c776fb5c6a9a740f84",
      "change_detected": true
    },
    {
      "timestamp": "2025-10-09T22:49:31Z",
      "status": "updated",
      "hash": "22e412aa4c7c8703b0468d50be20761d",
      "change_detected": true
    },
    {
      "timestamp": "2025-10-09T23:00:00Z",
      "status": "updated",
      "hash": "7c2c9a5000eb9741cbf765f506ba3eb2",
      "change_detected": true
    },
    {
      "timestamp": "2025-10-09T23:23:48Z",
      "status": "updated",
      "hash": "3bfbf3b0b6eb28d7b9e37483a3c9c0d2",
      "change_detected": true
    },
    {
      "timestamp": "2025-10-09T23:36:14Z",
      "status": "updated",
      "hash": "8e4fe7efde0a0c675eef2aaa89282b4f",
      "change_detected": true
    },
    {
      "timestamp": "2025-10-09T23:47:19Z",
      "status": "updated",
      "hash": "1c52a29a01b3bc68bdbd03fc009f8c46",
      "change_detected": true
    },
    {
      "timestamp": "2025-10-09T23:57:53Z",
      "status": "updated",
      "hash": "f7e9ede78c6b10dc2092a82622fa16b8",
      "change_detected": true
    },
    {
      "timestamp": "2025-10-10T01:53:36Z",
      "status": "updated",
      "hash": "d92b4022c662914ae160af566fa23e49",
      "change_detected": true
    },
    {
      "timestamp": "2025-10-10T02:58:03Z",
      "status": "updated",
      "hash": "cb2b701f8d3a632e61d026b1ffb2b784",
      "change_detected": true
    },
    {
      "timestamp": "2025-10-10T03:35:46Z",
      "status": "updated",
      "hash": "b19395074eb0cc6ba6a15fd7952b6f08",
      "change_detected": true
    },
    {
      "timestamp": "2025-10-10T03:52:24Z",
      "status": "updated",
      "hash": "47da40784d0e408847d1dc2938f65dec",
      "change_detected": true
    },
    {
      "timestamp": "2025-10-10T04:37:56Z",
      "status": "unchanged",
      "hash": "b8ed90b0e80b7d6afb7c8aa6543a36de",
      "change_detected": false
    },
    {
      "timestamp": "2025-10-10T04:50:09Z",
      "status": "updated",
      "hash": "7882b25dee250be9645312f8ef731fe4",
      "change_detected": true
    },
    {
      "timestamp": "2025-10-10T05:00:48Z",
      "status": "updated",
      "hash": "d7035883752b4cedb0bdc17944433dfd",
      "change_detected": true
    },
    {
      "timestamp": "2025-10-10T05:27:55Z",
      "status": "updated",
      "hash": "91f42f3392ccaa114f62c6f60b07d70b",
      "change_detected": true
    },
    {
      "timestamp": "2025-10-10T05:43:23Z",
      "status": "updated",
      "hash": "09619ac491c2cd57863eb0b17e827af6",
      "change_detected": true
    },
    {
      "timestamp": "2025-10-10T05:53:55Z",
      "status": "updated",
      "hash": "0db8cc097eb0862f8a227bc853c4c9b6",
      "change_detected": true
    },
    {
      "timestamp": "2025-10-10T06:24:21Z",
      "status": "updated",
      "hash": "0f0a90e917378f7a59849a537a513534",
      "change_detected": true
    },
    {
      "timestamp": "2025-10-10T06:49:32Z",
      "status": "updated",
      "hash": "997205bca37dd01bc0ea0c580071aa0e",
      "change_detected": true
    },
    {
      "timestamp": "2025-10-10T07:38:47Z",
      "status": "unchanged",
      "hash": "48018543ef530dcf9fa46837036d679a",
      "change_detected": false
    },
    {
      "timestamp": "2025-10-10T07:49:39Z",
      "status": "updated",
      "hash": "2c53181cb257711c73619410c35bb3bb",
      "change_detected": true
    },
    {
      "timestamp": "2025-10-10T08:00:29Z",
      "status": "updated",
      "hash": "f904d4b7b1e304304461aff4ed75d18a",
      "change_detected": true
    },
    {
      "timestamp": "2025-10-10T08:34:57Z",
      "status": "updated",
      "hash": "1f7c51fd4b43f631beafe10fa29a2bf5",
      "change_detected": true
    },
    {
      "timestamp": "2025-10-10T08:51:28Z",
      "status": "updated",
      "hash": "125194419915b9968a6d59796f2cd614",
      "change_detected": true
    },
    {
      "timestamp": "2025-10-10T09:12:45Z",
      "status": "updated",
      "hash": "236f3d81def5ef84cc45f8d03128f3f6",
      "change_detected": true
    },
    {
      "timestamp": "2025-10-10T09:33:03Z",
      "status": "updated",
      "hash": "15d0ca70cf9a0bfdb170d6158945b2f8",
      "change_detected": true
    },
    {
      "timestamp": "2025-10-10T09:45:05Z",
      "status": "updated",
      "hash": "0f6e82764e06ccf149bc58ad2e97b8f4",
      "change_detected": true
    },
    {
      "timestamp": "2025-10-10T09:55:46Z",
      "status": "updated",
      "hash": "e441b1a24b86c8d0a47b1de1c7b8590c",
      "change_detected": true
    },
    {
      "timestamp": "2025-10-10T10:21:35Z",
      "status": "updated",
      "hash": "a4337fc5091762ef8862d340625d70bd",
      "change_detected": true
    },
    {
      "timestamp": "2025-10-10T10:40:17Z",
      "status": "updated",
      "hash": "22006a5a173c722a5dfdde82a1d279ab",
      "change_detected": true
    },
    {
      "timestamp": "2025-10-10T10:51:16Z",
      "status": "updated",
      "hash": "b1a0d514cdd0d1147345e9443a713623",
      "change_detected": true
    },
    {
      "timestamp": "2025-10-10T11:09:20Z",
      "status": "updated",
      "hash": "8a1db1a63ea564bd70b9f7ddc18628d8",
      "change_detected": true
    },
    {
      "timestamp": "2025-10-10T11:26:17Z",
      "status": "updated",
      "hash": "0bb00f71180b9eb131e7b7c9e2bc8f8e",
      "change_detected": true
    },
    {
      "timestamp": "2025-10-10T11:49:24Z",
      "status": "unchanged",
      "hash": "774f03432ac853fc56d823c20e7346a2",
      "change_detected": false
    },
    {
      "timestamp": "2025-10-10T12:00:07Z",
      "status": "updated",
      "hash": "467a0220846ff96c09e5c697cd852970",
      "change_detected": true
    },
    {
      "timestamp": "2025-10-10T12:54:27Z",
      "status": "updated",
      "hash": "c7b54d0483359d26bcf811096fd34a09",
      "change_detected": true
    },
    {
      "timestamp": "2025-10-10T13:26:37Z",
      "status": "updated",
      "hash": "488ef13f924caf717ba100b213621d85",
      "change_detected": true
    },
    {
      "timestamp": "2025-10-10T13:45:00Z",
      "status": "updated",
      "hash": "e4e490c0e577dc32bd3212582a99720e",
      "change_detected": true
    },
    {
      "timestamp": "2025-10-10T13:55:44Z",
      "status": "updated",
      "hash": "b732b2e79ef7422e7144389f0598cb82",
      "change_detected": true
    },
    {
      "timestamp": "2025-10-10T14:39:21Z",
      "status": "unchanged",
      "hash": "ca66d0e07fc86064359fd0a295adf1f4",
      "change_detected": false
    },
    {
      "timestamp": "2025-10-10T14:50:23Z",
      "status": "updated",
      "hash": "5e8017727e91d8af5c7fcae5a56f3ab4",
      "change_detected": true
    },
    {
      "timestamp": "2025-10-10T15:27:44Z",
      "status": "unchanged",
      "hash": "822911f2906b107917eef46dc42ba9f7",
      "change_detected": false
    },
    {
      "timestamp": "2025-10-10T15:42:11Z",
      "status": "updated",
      "hash": "4ba2e78493c8e8c8a66af6a11e1db4b8",
      "change_detected": true
    },
    {
      "timestamp": "2025-10-10T15:52:58Z",
      "status": "updated",
      "hash": "4a1964f65d7c143d460ea7d37db6189a",
      "change_detected": true
    },
    {
      "timestamp": "2025-10-10T16:17:10Z",
      "status": "updated",
      "hash": "f1b3a166452581a80c458fc707cbfc98",
      "change_detected": true
    },
    {
      "timestamp": "2025-10-10T16:41:11Z",
      "status": "updated",
      "hash": "2f5c74db285939a82329e0180e30b384",
      "change_detected": true
    },
    {
      "timestamp": "2025-10-10T16:53:26Z",
      "status": "updated",
      "hash": "bf7dab6662a9ac6c533bd16a8771d56c",
      "change_detected": true
    },
    {
      "timestamp": "2025-10-10T17:13:54Z",
      "status": "updated",
      "hash": "983b16a5e5f1689dcf990272d7babd1c",
      "change_detected": true
    },
    {
      "timestamp": "2025-10-10T17:31:13Z",
      "status": "updated",
      "hash": "d5d2d217bca6b305b5f3f0f269701daf",
      "change_detected": true
    },
    {
      "timestamp": "2025-10-10T17:42:54Z",
      "status": "updated",
      "hash": "6e3549af8daaa179da7d19a9e27c1cc8",
      "change_detected": true
    },
    {
      "timestamp": "2025-10-10T17:53:41Z",
      "status": "updated",
      "hash": "430b41428a6c9199a1f63b7963718c0f",
      "change_detected": true
    },
    {
      "timestamp": "2025-10-10T18:22:26Z",
      "status": "updated",
      "hash": "d6fda74537c77a2ef43bd19af3da19a1",
      "change_detected": true
    },
    {
      "timestamp": "2025-10-10T18:45:11Z",
      "status": "updated",
      "hash": "bdaaa79e71979b515253854060ae2e5a",
      "change_detected": true
    },
    {
      "timestamp": "2025-10-10T18:55:45Z",
      "status": "updated",
      "hash": "bd01b48c22fc75328b9797fa3465a46a",
      "change_detected": true
    },
    {
      "timestamp": "2025-10-10T19:16:02Z",
      "status": "updated",
      "hash": "650f7a42c027ec6a5a528c048ebe8865",
      "change_detected": true
    },
    {
      "timestamp": "2025-10-10T19:28:14Z",
      "status": "updated",
      "hash": "23989276f2c74fc5c4e160f51b2087dc",
      "change_detected": true
    },
    {
      "timestamp": "2025-10-10T19:39:56Z",
      "status": "updated",
      "hash": "894a6179c884b409a27457f92173201c",
      "change_detected": true
    },
    {
      "timestamp": "2025-10-10T19:50:35Z",
      "status": "updated",
      "hash": "160381963f8f9e311cbb145557593913",
      "change_detected": true
    },
    {
      "timestamp": "2025-10-10T20:12:30Z",
      "status": "updated",
      "hash": "31e954d2d8d2c038252ff1848b12507b",
      "change_detected": true
    },
    {
      "timestamp": "2025-10-10T20:31:39Z",
      "status": "updated",
      "hash": "ccbb64bd31b91f1be2e391494ba2a38f",
      "change_detected": true
    },
    {
      "timestamp": "2025-10-10T20:55:14Z",
      "status": "unchanged",
      "hash": "4175f61ee566cb21f5b67ebe8af2cb5a",
      "change_detected": false
    },
    {
      "timestamp": "2025-10-10T21:15:46Z",
      "status": "updated",
      "hash": "b3ef5559b0d84a3b39dfaa33abe2eb98",
      "change_detected": true
    },
    {
      "timestamp": "2025-10-10T21:29:28Z",
      "status": "updated",
      "hash": "194979dc7f101f251c010d515ebff8ad",
      "change_detected": true
    },
    {
      "timestamp": "2025-10-10T21:40:18Z",
      "status": "updated",
      "hash": "6910c0577764141ce93c9d322669478c",
      "change_detected": true
    },
    {
      "timestamp": "2025-10-10T21:51:15Z",
      "status": "updated",
      "hash": "7308ed784f1a5d3a64478a482f213d79",
      "change_detected": true
    },
    {
      "timestamp": "2025-10-10T22:09:08Z",
      "status": "updated",
      "hash": "f5c3255f2189c6b4266ce866fc06ed09",
      "change_detected": true
    },
    {
      "timestamp": "2025-10-10T22:29:59Z",
      "status": "updated",
      "hash": "f0a71c36ac22ec0957afdf5cf847e037",
      "change_detected": true
    },
    {
      "timestamp": "2025-10-10T22:42:27Z",
      "status": "updated",
      "hash": "e95560c7bb20287bff61d48dec44c818",
      "change_detected": true
    },
    {
      "timestamp": "2025-10-10T22:53:08Z",
      "status": "updated",
      "hash": "0e830f30a95766dcbb337a631774700a",
      "change_detected": true
    },
    {
      "timestamp": "2025-10-10T23:28:18Z",
      "status": "unchanged",
      "hash": "fe044af663abb8e788cbe48c21651f68",
      "change_detected": false
    },
    {
      "timestamp": "2025-10-10T23:39:45Z",
      "status": "updated",
      "hash": "2bebd7726cb6eee599a0713e40f58d2b",
      "change_detected": true
    },
    {
      "timestamp": "2025-10-10T23:50:41Z",
      "status": "updated",
      "hash": "91a6631b4c0be95c5e535f415c90400b",
      "change_detected": true
    },
    {
      "timestamp": "2025-10-11T00:38:56Z",
      "status": "updated",
      "hash": "93613ad4c12c1943defaf1db88c26ef0",
      "change_detected": true
    },
    {
      "timestamp": "2025-10-11T02:08:42Z",
      "status": "updated",
      "hash": "bf07c543fb81046a6845886c2850012f",
      "change_detected": true
    },
    {
      "timestamp": "2025-10-11T03:33:30Z",
      "status": "unchanged",
      "hash": "91f6bc4e07a6a738d3cf61c763a9a7a6",
      "change_detected": false
    },
    {
      "timestamp": "2025-10-11T03:46:50Z",
      "status": "updated",
      "hash": "5faa5eff67479ccdb36704d2f15998cd",
      "change_detected": true
    },
    {
      "timestamp": "2025-10-11T03:57:19Z",
      "status": "updated",
      "hash": "44bd8c2747a19262e557ee25e584d27b",
      "change_detected": true
    },
    {
      "timestamp": "2025-10-11T04:26:36Z",
      "status": "updated",
      "hash": "beabb52404863cdb4e944f2189485f79",
      "change_detected": true
    },
    {
      "timestamp": "2025-10-11T04:41:43Z",
      "status": "updated",
      "hash": "fec98db25c2cbcb7fcf801920e5a2646",
      "change_detected": true
    },
    {
      "timestamp": "2025-10-11T04:52:31Z",
      "status": "updated",
      "hash": "9019b8a88877dcec4fef4fabea85c8c2",
      "change_detected": true
    },
    {
      "timestamp": "2025-10-11T05:11:57Z",
      "status": "updated",
      "hash": "0fa709ef030b46f1b8cfa050a6d89f57",
      "change_detected": true
    },
    {
      "timestamp": "2025-10-11T05:31:15Z",
      "status": "updated",
      "hash": "c0f5f315505b721cf975a2a0549e8195",
      "change_detected": true
    },
    {
      "timestamp": "2025-10-11T05:43:01Z",
      "status": "updated",
      "hash": "2d87990b40c16550328790454fc72c1a",
      "change_detected": true
    },
    {
      "timestamp": "2025-10-11T05:53:57Z",
      "status": "updated",
      "hash": "194397a855e4d2f956921a021ef97f75",
      "change_detected": true
    },
    {
      "timestamp": "2025-10-11T06:21:20Z",
      "status": "updated",
      "hash": "bc21a9ec85b9cd6940c9717b08222f1f",
      "change_detected": true
    },
    {
      "timestamp": "2025-10-11T06:42:49Z",
      "status": "updated",
      "hash": "6eac6f042123725a593cfdf6fdc598af",
      "change_detected": true
    }
  ],
  "twitter": [
    {
      "timestamp": "2025-10-09T21:24:49Z",
      "status": "unchanged",
      "hash": "b28c8755ac993731f3fe2ba4901b3be5",
      "change_detected": false
    },
    {
      "timestamp": "2025-10-09T21:36:59Z",
      "status": "unchanged",
      "hash": "b28c8755ac993731f3fe2ba4901b3be5",
      "change_detected": false
    },
    {
      "timestamp": "2025-10-09T21:48:02Z",
      "status": "unchanged",
      "hash": "b28c8755ac993731f3fe2ba4901b3be5",
      "change_detected": false
    },
    {
      "timestamp": "2025-10-09T21:58:27Z",
      "status": "unchanged",
      "hash": "b28c8755ac993731f3fe2ba4901b3be5",
      "change_detected": false
    },
    {
      "timestamp": "2025-10-09T22:24:37Z",
      "status": "unchanged",
      "hash": "b28c8755ac993731f3fe2ba4901b3be5",
      "change_detected": false
    },
    {
      "timestamp": "2025-10-09T22:39:08Z",
      "status": "unchanged",
      "hash": "b28c8755ac993731f3fe2ba4901b3be5",
      "change_detected": false
    },
    {
      "timestamp": "2025-10-09T22:49:38Z",
      "status": "unchanged",
      "hash": "b28c8755ac993731f3fe2ba4901b3be5",
      "change_detected": false
    },
    {
      "timestamp": "2025-10-09T23:00:07Z",
      "status": "unchanged",
      "hash": "b28c8755ac993731f3fe2ba4901b3be5",
      "change_detected": false
    },
    {
      "timestamp": "2025-10-09T23:23:56Z",
      "status": "unchanged",
      "hash": "b28c8755ac993731f3fe2ba4901b3be5",
      "change_detected": false
    },
    {
      "timestamp": "2025-10-09T23:36:22Z",
      "status": "unchanged",
      "hash": "b28c8755ac993731f3fe2ba4901b3be5",
      "change_detected": false
    },
    {
      "timestamp": "2025-10-09T23:47:27Z",
      "status": "unchanged",
      "hash": "b28c8755ac993731f3fe2ba4901b3be5",
      "change_detected": false
    },
    {
      "timestamp": "2025-10-09T23:58:01Z",
      "status": "updated",
      "hash": "d5c56b81d9a6a0bf7261169acd59fb7b",
      "change_detected": true
    },
    {
      "timestamp": "2025-10-10T01:53:43Z",
      "status": "updated",
      "hash": "c9c844b5d32d0cc16fc0fcbbc109a93d",
      "change_detected": true
    },
    {
      "timestamp": "2025-10-10T02:58:12Z",
      "status": "unchanged",
      "hash": "c9c844b5d32d0cc16fc0fcbbc109a93d",
      "change_detected": false
    },
    {
      "timestamp": "2025-10-10T03:35:54Z",
      "status": "unchanged",
      "hash": "c9c844b5d32d0cc16fc0fcbbc109a93d",
      "change_detected": false
    },
    {
      "timestamp": "2025-10-10T03:52:31Z",
      "status": "unchanged",
      "hash": "c9c844b5d32d0cc16fc0fcbbc109a93d",
      "change_detected": false
    },
    {
      "timestamp": "2025-10-10T04:15:29Z",
      "status": "updated",
      "hash": "3145cc30613dfa49c062c1b585f84d7f",
      "change_detected": true
    },
    {
      "timestamp": "2025-10-10T04:38:04Z",
      "status": "updated",
      "hash": "c9c844b5d32d0cc16fc0fcbbc109a93d",
      "change_detected": true
    },
    {
      "timestamp": "2025-10-10T04:50:16Z",
      "status": "unchanged",
      "hash": "c9c844b5d32d0cc16fc0fcbbc109a93d",
      "change_detected": false
    },
    {
      "timestamp": "2025-10-10T05:00:56Z",
      "status": "unchanged",
      "hash": "c9c844b5d32d0cc16fc0fcbbc109a93d",
      "change_detected": false
    },
    {
      "timestamp": "2025-10-10T05:28:03Z",
      "status": "unchanged",
      "hash": "c9c844b5d32d0cc16fc0fcbbc109a93d",
      "change_detected": false
    },
    {
      "timestamp": "2025-10-10T05:43:30Z",
      "status": "unchanged",
      "hash": "c9c844b5d32d0cc16fc0fcbbc109a93d",
      "change_detected": false
    },
    {
      "timestamp": "2025-10-10T05:54:02Z",
      "status": "unchanged",
      "hash": "c9c844b5d32d0cc16fc0fcbbc109a93d",
      "change_detected": false
    },
    {
      "timestamp": "2025-10-10T06:24:28Z",
      "status": "unchanged",
      "hash": "c9c844b5d32d0cc16fc0fcbbc109a93d",
      "change_detected": false
    },
    {
      "timestamp": "2025-10-10T06:49:40Z",
      "status": "unchanged",
      "hash": "c9c844b5d32d0cc16fc0fcbbc109a93d",
      "change_detected": false
    },
    {
      "timestamp": "2025-10-10T07:00:33Z",
      "status": "unchanged",
      "hash": "c9c844b5d32d0cc16fc0fcbbc109a93d",
      "change_detected": false
    },
    {
      "timestamp": "2025-10-10T07:25:57Z",
      "status": "unchanged",
      "hash": "c9c844b5d32d0cc16fc0fcbbc109a93d",
      "change_detected": false
    },
    {
      "timestamp": "2025-10-10T07:38:55Z",
      "status": "unchanged",
      "hash": "c9c844b5d32d0cc16fc0fcbbc109a93d",
      "change_detected": false
    },
    {
      "timestamp": "2025-10-10T07:49:47Z",
      "status": "unchanged",
      "hash": "c9c844b5d32d0cc16fc0fcbbc109a93d",
      "change_detected": false
    },
    {
      "timestamp": "2025-10-10T08:00:37Z",
      "status": "unchanged",
      "hash": "c9c844b5d32d0cc16fc0fcbbc109a93d",
      "change_detected": false
    },
    {
      "timestamp": "2025-10-10T08:35:05Z",
      "status": "unchanged",
      "hash": "c9c844b5d32d0cc16fc0fcbbc109a93d",
      "change_detected": false
    },
    {
      "timestamp": "2025-10-10T08:51:36Z",
      "status": "unchanged",
      "hash": "c9c844b5d32d0cc16fc0fcbbc109a93d",
      "change_detected": false
    },
    {
      "timestamp": "2025-10-10T09:12:52Z",
      "status": "unchanged",
      "hash": "c9c844b5d32d0cc16fc0fcbbc109a93d",
      "change_detected": false
    },
    {
      "timestamp": "2025-10-10T09:33:10Z",
      "status": "unchanged",
      "hash": "c9c844b5d32d0cc16fc0fcbbc109a93d",
      "change_detected": false
    },
    {
      "timestamp": "2025-10-10T09:45:12Z",
      "status": "unchanged",
      "hash": "c9c844b5d32d0cc16fc0fcbbc109a93d",
      "change_detected": false
    },
    {
      "timestamp": "2025-10-10T09:55:54Z",
      "status": "unchanged",
      "hash": "c9c844b5d32d0cc16fc0fcbbc109a93d",
      "change_detected": false
    },
    {
      "timestamp": "2025-10-10T10:21:44Z",
      "status": "unchanged",
      "hash": "c9c844b5d32d0cc16fc0fcbbc109a93d",
      "change_detected": false
    },
    {
      "timestamp": "2025-10-10T10:40:24Z",
      "status": "unchanged",
      "hash": "c9c844b5d32d0cc16fc0fcbbc109a93d",
      "change_detected": false
    },
    {
      "timestamp": "2025-10-10T10:51:23Z",
      "status": "unchanged",
      "hash": "c9c844b5d32d0cc16fc0fcbbc109a93d",
      "change_detected": false
    },
    {
      "timestamp": "2025-10-10T11:09:28Z",
      "status": "unchanged",
      "hash": "c9c844b5d32d0cc16fc0fcbbc109a93d",
      "change_detected": false
    },
    {
      "timestamp": "2025-10-10T11:26:25Z",
      "status": "unchanged",
      "hash": "c9c844b5d32d0cc16fc0fcbbc109a93d",
      "change_detected": false
    },
    {
      "timestamp": "2025-10-10T11:38:25Z",
      "status": "unchanged",
      "hash": "c9c844b5d32d0cc16fc0fcbbc109a93d",
      "change_detected": false
    },
    {
      "timestamp": "2025-10-10T11:49:31Z",
      "status": "unchanged",
      "hash": "c9c844b5d32d0cc16fc0fcbbc109a93d",
      "change_detected": false
    },
    {
      "timestamp": "2025-10-10T12:00:14Z",
      "status": "unchanged",
      "hash": "c9c844b5d32d0cc16fc0fcbbc109a93d",
      "change_detected": false
    },
    {
      "timestamp": "2025-10-10T12:54:34Z",
      "status": "unchanged",
      "hash": "c9c844b5d32d0cc16fc0fcbbc109a93d",
      "change_detected": false
    },
    {
      "timestamp": "2025-10-10T13:26:44Z",
      "status": "unchanged",
      "hash": "c9c844b5d32d0cc16fc0fcbbc109a93d",
      "change_detected": false
    },
    {
      "timestamp": "2025-10-10T13:45:08Z",
      "status": "unchanged",
      "hash": "c9c844b5d32d0cc16fc0fcbbc109a93d",
      "change_detected": false
    },
    {
      "timestamp": "2025-10-10T13:55:51Z",
      "status": "unchanged",
      "hash": "c9c844b5d32d0cc16fc0fcbbc109a93d",
      "change_detected": false
    },
    {
      "timestamp": "2025-10-10T14:19:59Z",
      "status": "unchanged",
      "hash": "c9c844b5d32d0cc16fc0fcbbc109a93d",
      "change_detected": false
    },
    {
      "timestamp": "2025-10-10T14:39:28Z",
      "status": "unchanged",
      "hash": "c9c844b5d32d0cc16fc0fcbbc109a93d",
      "change_detected": false
    },
    {
      "timestamp": "2025-10-10T14:50:31Z",
      "status": "unchanged",
      "hash": "c9c844b5d32d0cc16fc0fcbbc109a93d",
      "change_detected": false
    },
    {
      "timestamp": "2025-10-10T15:01:41Z",
      "status": "unchanged",
      "hash": "c9c844b5d32d0cc16fc0fcbbc109a93d",
      "change_detected": false
    },
    {
      "timestamp": "2025-10-10T15:27:51Z",
      "status": "unchanged",
      "hash": "c9c844b5d32d0cc16fc0fcbbc109a93d",
      "change_detected": false
    },
    {
      "timestamp": "2025-10-10T15:42:19Z",
      "status": "unchanged",
      "hash": "c9c844b5d32d0cc16fc0fcbbc109a93d",
      "change_detected": false
    },
    {
      "timestamp": "2025-10-10T15:53:05Z",
      "status": "unchanged",
      "hash": "c9c844b5d32d0cc16fc0fcbbc109a93d",
      "change_detected": false
    },
    {
      "timestamp": "2025-10-10T16:17:18Z",
      "status": "unchanged",
      "hash": "c9c844b5d32d0cc16fc0fcbbc109a93d",
      "change_detected": false
    },
    {
      "timestamp": "2025-10-10T16:41:19Z",
      "status": "unchanged",
      "hash": "c9c844b5d32d0cc16fc0fcbbc109a93d",
      "change_detected": false
    },
    {
      "timestamp": "2025-10-10T16:53:34Z",
      "status": "unchanged",
      "hash": "c9c844b5d32d0cc16fc0fcbbc109a93d",
      "change_detected": false
    },
    {
      "timestamp": "2025-10-10T17:14:01Z",
      "status": "unchanged",
      "hash": "c9c844b5d32d0cc16fc0fcbbc109a93d",
      "change_detected": false
    },
    {
      "timestamp": "2025-10-10T17:31:20Z",
      "status": "unchanged",
      "hash": "c9c844b5d32d0cc16fc0fcbbc109a93d",
      "change_detected": false
    },
    {
      "timestamp": "2025-10-10T17:43:01Z",
      "status": "unchanged",
      "hash": "c9c844b5d32d0cc16fc0fcbbc109a93d",
      "change_detected": false
    },
    {
      "timestamp": "2025-10-10T17:53:49Z",
      "status": "unchanged",
      "hash": "c9c844b5d32d0cc16fc0fcbbc109a93d",
      "change_detected": false
    },
    {
      "timestamp": "2025-10-10T18:22:35Z",
      "status": "unchanged",
      "hash": "c9c844b5d32d0cc16fc0fcbbc109a93d",
      "change_detected": false
    },
    {
      "timestamp": "2025-10-10T18:45:19Z",
      "status": "unchanged",
      "hash": "c9c844b5d32d0cc16fc0fcbbc109a93d",
      "change_detected": false
    },
    {
      "timestamp": "2025-10-10T18:55:53Z",
      "status": "unchanged",
      "hash": "c9c844b5d32d0cc16fc0fcbbc109a93d",
      "change_detected": false
    },
    {
      "timestamp": "2025-10-10T19:16:09Z",
      "status": "unchanged",
      "hash": "c9c844b5d32d0cc16fc0fcbbc109a93d",
      "change_detected": false
    },
    {
      "timestamp": "2025-10-10T19:28:22Z",
      "status": "unchanged",
      "hash": "c9c844b5d32d0cc16fc0fcbbc109a93d",
      "change_detected": false
    },
    {
      "timestamp": "2025-10-10T19:40:04Z",
      "status": "unchanged",
      "hash": "c9c844b5d32d0cc16fc0fcbbc109a93d",
      "change_detected": false
    },
    {
      "timestamp": "2025-10-10T19:50:42Z",
      "status": "unchanged",
      "hash": "c9c844b5d32d0cc16fc0fcbbc109a93d",
      "change_detected": false
    },
    {
      "timestamp": "2025-10-10T20:12:38Z",
      "status": "updated",
      "hash": "af53dd7b63911ac901bfbec7dda7eb80",
      "change_detected": true
    },
    {
      "timestamp": "2025-10-10T20:31:46Z",
      "status": "unchanged",
      "hash": "af53dd7b63911ac901bfbec7dda7eb80",
      "change_detected": false
    },
    {
      "timestamp": "2025-10-10T20:44:36Z",
      "status": "updated",
      "hash": "6d12f6771b36a25267e2b965ba3f0129",
      "change_detected": true
    },
    {
      "timestamp": "2025-10-10T20:55:22Z",
      "status": "updated",
      "hash": "af53dd7b63911ac901bfbec7dda7eb80",
      "change_detected": true
    },
    {
      "timestamp": "2025-10-10T21:15:53Z",
      "status": "updated",
      "hash": "c9c844b5d32d0cc16fc0fcbbc109a93d",
      "change_detected": true
    },
    {
      "timestamp": "2025-10-10T21:29:35Z",
      "status": "updated",
      "hash": "af53dd7b63911ac901bfbec7dda7eb80",
      "change_detected": true
    },
    {
      "timestamp": "2025-10-10T21:40:25Z",
      "status": "updated",
      "hash": "c9c844b5d32d0cc16fc0fcbbc109a93d",
      "change_detected": true
    },
    {
      "timestamp": "2025-10-10T21:51:22Z",
      "status": "unchanged",
      "hash": "c9c844b5d32d0cc16fc0fcbbc109a93d",
      "change_detected": false
    },
    {
      "timestamp": "2025-10-10T22:09:16Z",
      "status": "updated",
      "hash": "af53dd7b63911ac901bfbec7dda7eb80",
      "change_detected": true
    },
    {
      "timestamp": "2025-10-10T22:30:06Z",
      "status": "updated",
      "hash": "c9c844b5d32d0cc16fc0fcbbc109a93d",
      "change_detected": true
    },
    {
      "timestamp": "2025-10-10T22:42:35Z",
      "status": "updated",
      "hash": "af53dd7b63911ac901bfbec7dda7eb80",
      "change_detected": true
    },
    {
      "timestamp": "2025-10-10T22:53:16Z",
      "status": "updated",
      "hash": "c9c844b5d32d0cc16fc0fcbbc109a93d",
      "change_detected": true
    },
    {
      "timestamp": "2025-10-10T23:12:28Z",
      "status": "unchanged",
      "hash": "c9c844b5d32d0cc16fc0fcbbc109a93d",
      "change_detected": false
    },
    {
      "timestamp": "2025-10-10T23:28:27Z",
      "status": "unchanged",
      "hash": "c9c844b5d32d0cc16fc0fcbbc109a93d",
      "change_detected": false
    },
    {
      "timestamp": "2025-10-10T23:39:52Z",
      "status": "unchanged",
      "hash": "c9c844b5d32d0cc16fc0fcbbc109a93d",
      "change_detected": false
    },
    {
      "timestamp": "2025-10-10T23:50:48Z",
      "status": "unchanged",
      "hash": "c9c844b5d32d0cc16fc0fcbbc109a93d",
      "change_detected": false
    },
    {
      "timestamp": "2025-10-11T00:39:04Z",
      "status": "unchanged",
      "hash": "c9c844b5d32d0cc16fc0fcbbc109a93d",
      "change_detected": false
    },
    {
      "timestamp": "2025-10-11T02:08:50Z",
      "status": "unchanged",
      "hash": "c9c844b5d32d0cc16fc0fcbbc109a93d",
      "change_detected": false
    },
    {
      "timestamp": "2025-10-11T03:02:19Z",
      "status": "unchanged",
      "hash": "c9c844b5d32d0cc16fc0fcbbc109a93d",
      "change_detected": false
    },
    {
      "timestamp": "2025-10-11T03:33:38Z",
      "status": "unchanged",
      "hash": "c9c844b5d32d0cc16fc0fcbbc109a93d",
      "change_detected": false
    },
    {
      "timestamp": "2025-10-11T03:46:57Z",
      "status": "unchanged",
      "hash": "c9c844b5d32d0cc16fc0fcbbc109a93d",
      "change_detected": false
    },
    {
      "timestamp": "2025-10-11T03:57:28Z",
      "status": "unchanged",
      "hash": "c9c844b5d32d0cc16fc0fcbbc109a93d",
      "change_detected": false
    },
    {
      "timestamp": "2025-10-11T04:26:44Z",
      "status": "unchanged",
      "hash": "c9c844b5d32d0cc16fc0fcbbc109a93d",
      "change_detected": false
    },
    {
      "timestamp": "2025-10-11T04:41:51Z",
      "status": "unchanged",
      "hash": "c9c844b5d32d0cc16fc0fcbbc109a93d",
      "change_detected": false
    },
    {
      "timestamp": "2025-10-11T04:52:38Z",
      "status": "unchanged",
      "hash": "c9c844b5d32d0cc16fc0fcbbc109a93d",
      "change_detected": false
    },
    {
      "timestamp": "2025-10-11T05:12:05Z",
      "status": "unchanged",
      "hash": "c9c844b5d32d0cc16fc0fcbbc109a93d",
      "change_detected": false
    },
    {
      "timestamp": "2025-10-11T05:31:23Z",
      "status": "unchanged",
      "hash": "c9c844b5d32d0cc16fc0fcbbc109a93d",
      "change_detected": false
    },
    {
      "timestamp": "2025-10-11T05:43:08Z",
      "status": "unchanged",
      "hash": "c9c844b5d32d0cc16fc0fcbbc109a93d",
      "change_detected": false
    },
    {
      "timestamp": "2025-10-11T05:54:05Z",
      "status": "updated",
      "hash": "3145cc30613dfa49c062c1b585f84d7f",
      "change_detected": true
    },
    {
      "timestamp": "2025-10-11T06:21:30Z",
      "status": "updated",
      "hash": "c9c844b5d32d0cc16fc0fcbbc109a93d",
      "change_detected": true
    },
    {
      "timestamp": "2025-10-11T06:42:57Z",
      "status": "unchanged",
      "hash": "c9c844b5d32d0cc16fc0fcbbc109a93d",
      "change_detected": false
    }
  ]
}