{
  "last_updated": "2025-09-12T13:54:52Z",
  "sites": [
    {
      "id": "cookpad",
      "name": "Cookpad Web",
      "url": "p0mbSZJAmMerAjTP+aZzP29uJgeMCFNRWR43mbUw1rMU9ATKEzOlooHK+pfY\n781w",
      "status": "updated",
      "last_check": "2025-09-12T13:54:36Z",
      "last_change": "2025-09-12T13:54:36Z",
      "hash": "af9fb910b2cc2e2aca0c9b949f9fba73",
      "error": null,
      "encrypted": true
    },
    {
      "id": "test",
      "name": "アレ",
      "url": "2e8dfTtZ1CwH55hmGrJIXXJEOOoyyIlZOFdvpTPkdFtjKB5lg9pUopXhtgc6\nfcqGrLO85X5uiSXiI4tYQTLSLPWopSQb71CFQkQc8YLM+qUj/ks+Zh3bWSyW\nFSFReRyjzc5fQLdvbwTVYtDDFX7uQg==",
      "status": "unchanged",
      "last_check": "2025-09-12T13:54:45Z",
      "last_change": null,
      "hash": "93106e0343de1314f1ed17897c708011",
      "error": null,
      "encrypted": true
    },
    {
      "id": "test2",
      "name": "全体",
      "url": "abaewURgjBPIyavGmD1HPKqBmyCKP9nYNk6Qg03Dbx+pUr+zjcXZJUH9Popd\nossK",
      "status": "updated",
      "last_check": "2025-09-12T13:54:52Z",
      "last_change": "2025-09-12T13:54:52Z",
      "hash": "5f3452d736c65071bcc37511dfb719ef",
      "error": null,
      "encrypted": true
    },
    {
      "id": "twitter",
      "name": "twitter",
      "url": "7buPUraCACW1J84z8GSr6AsoKqT61dBYf5iT1WqeUQrD9sctclaBhB6d661v\nPO5p",
      "status": "unchanged",
      "last_check": "2025-09-12T13:55:00Z",
      "last_change": "2025-09-11T20:20:02Z",
      "hash": "ad5680d9e5dccd5b80cf9bb75c508bad",
      "error": null,
      "encrypted": true
    }
  ]
}