{
  "last_updated": "2025-10-17T00:00:45Z",
  "sites": [
    {
      "id": "cookpad",
      "name": "Cookpad Web",
      "url": "p0mbSZJAmMerAjTP+aZzP29uJgeMCFNRWR43mbUw1rMU9ATKEzOlooHK+pfY\n781w",
      "status": "updated",
      "last_check": "2025-10-17T00:00:30Z",
      "last_change": "2025-10-17T00:00:30Z",
      "hash": "84e647d6ae66ad6e9c69333062a6c180",
      "error": null,
      "encrypted": true
    },
    {
      "id": "test",
      "name": "アレ",
      "url": "2e8dfTtZ1CwH55hmGrJIXXJEOOoyyIlZOFdvpTPkdFtjKB5lg9pUopXhtgc6\nfcqGrLO85X5uiSXiI4tYQTLSLPWopSQb71CFQkQc8YLM+qUj/ks+Zh3bWSyW\nFSFReRyjzc5fQLdvbwTVYtDDFX7uQg==",
      "status": "unchanged",
      "last_check": "2025-10-17T00:00:38Z",
      "last_change": null,
      "hash": "dcd7ac68e82ffa8e7994b44707a6fd3a",
      "error": null,
      "encrypted": true
    },
    {
      "id": "test2",
      "name": "全体",
      "url": "abaewURgjBPIyavGmD1HPKqBmyCKP9nYNk6Qg03Dbx+pUr+zjcXZJUH9Popd\nossK",
      "status": "updated",
      "last_check": "2025-10-17T00:00:45Z",
      "last_change": "2025-10-17T00:00:45Z",
      "hash": "9040f1f7c869b1f5be5cefeaf1b58fec",
      "error": null,
      "encrypted": true
    },
    {
      "id": "twitter",
      "name": "twitter",
      "url": "7buPUraCACW1J84z8GSr6AsoKqT61dBYf5iT1WqeUQrD9sctclaBhB6d661v\nPO5p",
      "status": "unchanged",
      "last_check": "2025-10-17T00:00:53Z",
      "last_change": "2025-10-16T22:42:02Z",
      "hash": "2f5ab079c3dece0c8a808b7260f54c23",
      "error": null,
      "encrypted": true
    }
  ]
}