{
  "last_updated": "2025-08-31T05:24:14Z",
  "sites": [
    {
      "id": "cookpad",
      "name": "Cookpad Web",
      "url": "p0mbSZJAmMerAjTP+aZzP29uJgeMCFNRWR43mbUw1rMU9ATKEzOlooHK+pfY\n781w",
      "status": "updated",
      "last_check": "2025-08-31T05:23:57Z",
      "last_change": "2025-08-31T05:23:57Z",
      "hash": "0e89afe63cdfe625d7855b33fa28982d",
      "error": null,
      "encrypted": true
    },
    {
      "id": "test",
      "name": "アレ",
      "url": "2e8dfTtZ1CwH55hmGrJIXXJEOOoyyIlZOFdvpTPkdFtjKB5lg9pUopXhtgc6\nfcqGrLO85X5uiSXiI4tYQTLSLPWopSQb71CFQkQc8YLM+qUj/ks+Zh3bWSyW\nFSFReRyjzc5fQLdvbwTVYtDDFX7uQg==",
      "status": "unchanged",
      "last_check": "2025-08-31T05:24:06Z",
      "last_change": "2025-08-31T03:52:12Z",
      "hash": "37dfbe24afedae64906bcbbcd5afc46e",
      "error": null,
      "encrypted": true
    },
    {
      "id": "test2",
      "name": "全体",
      "url": "abaewURgjBPIyavGmD1HPKqBmyCKP9nYNk6Qg03Dbx+pUr+zjcXZJUH9Popd\nossK",
      "status": "updated",
      "last_check": "2025-08-31T05:24:14Z",
      "last_change": "2025-08-31T05:24:14Z",
      "hash": "21fbfb7dc97cebd1f61a419ddf39c441",
      "error": null,
      "encrypted": true
    },
    {
      "id": "twitter",
      "name": "twitter",
      "url": "7buPUraCACW1J84z8GSr6AsoKqT61dBYf5iT1WqeUQrD9sctclaBhB6d661v\nPO5p",
      "status": "unchanged",
      "last_check": "2025-08-31T05:24:22Z",
      "last_change": "2025-08-29T07:32:04Z",
      "hash": "62920c7a2b66d8094415b289354c893b",
      "error": null,
      "encrypted": true
    }
  ]
}